tcpyPI/__init__.py
tcpyPI/constants.py
tcpyPI/numba.py
tcpyPI/pi.py
tcpyPI/utilities.py
tcpypi-1.4.dist-info/METADATA
tcpypi-1.4.dist-info/WHEEL
tcpypi-1.4.dist-info/licenses/LICENSE
tcpypi-1.4.dist-info/RECORD
