Metadata-Version: 2.4
Name: tcpyPI
Version: 1.4
Summary: tcpyPI: Tropical cyclone potential intensity calculations in Python
Project-URL: Homepage, https://github.com/dgilford/tcpyPI
Project-URL: Download, https://github.com/dgilford/tcpyPI
Author-email: "Daniel M. Gilford, PhD" <dgilford@climatecentral.org>
License: MIT License
License-File: LICENSE
Classifier: License :: OSI Approved :: MIT License
Classifier: Operating System :: OS Independent
Classifier: Programming Language :: Python :: 3
Requires-Python: >=3.7
Requires-Dist: numba>=0.51.2
Requires-Dist: numpy>=1.19.5
